snowflake_semantic_tools/__init__.py
snowflake_semantic_tools/_version.py
snowflake_semantic_tools/core/__init__.py
snowflake_semantic_tools/core/enrichment/__init__.py
snowflake_semantic_tools/core/enrichment/cortex_synonym_generator.py
snowflake_semantic_tools/core/enrichment/metadata_enricher.py
snowflake_semantic_tools/core/enrichment/primary_key_validator.py
snowflake_semantic_tools/core/enrichment/type_mappings.py
snowflake_semantic_tools/core/enrichment/yaml_handler.py
snowflake_semantic_tools/core/generation/__init__.py
snowflake_semantic_tools/core/generation/semantic_view_builder.py
snowflake_semantic_tools/core/models/__init__.py
snowflake_semantic_tools/core/models/dbt_model.py
snowflake_semantic_tools/core/models/schemas.py
snowflake_semantic_tools/core/models/semantic_model.py
snowflake_semantic_tools/core/models/validation.py
snowflake_semantic_tools/core/parsing/__init__.py
snowflake_semantic_tools/core/parsing/file_detector.py
snowflake_semantic_tools/core/parsing/join_condition_parser.py
snowflake_semantic_tools/core/parsing/parser.py
snowflake_semantic_tools/core/parsing/parsers/__init__.py
snowflake_semantic_tools/core/parsing/parsers/data_extractors.py
snowflake_semantic_tools/core/parsing/parsers/dbt_parser.py
snowflake_semantic_tools/core/parsing/parsers/error_handler.py
snowflake_semantic_tools/core/parsing/parsers/manifest_parser.py
snowflake_semantic_tools/core/parsing/parsers/semantic_parser.py
snowflake_semantic_tools/core/parsing/parsers/table_summarizer.py
snowflake_semantic_tools/core/parsing/template_engine/__init__.py
snowflake_semantic_tools/core/parsing/template_engine/resolver.py
snowflake_semantic_tools/core/parsing/template_engine/validators.py
snowflake_semantic_tools/core/validation/__init__.py
snowflake_semantic_tools/core/validation/constants.py
snowflake_semantic_tools/core/validation/rules/__init__.py
snowflake_semantic_tools/core/validation/rules/dbt_models.py
snowflake_semantic_tools-0.1.1.dist-info/METADATA
snowflake_semantic_tools-0.1.1.dist-info/WHEEL
snowflake_semantic_tools-0.1.1.dist-info/entry_points.txt
snowflake_semantic_tools-0.1.1.dist-info/licenses/LICENSE
snowflake_semantic_tools-0.1.1.dist-info/RECORD
