Metadata-Version: 2.4
Name: snowflake-semantic-tools
Version: 0.1.1
Summary: dbt extension for managing Snowflake Semantic Views and Cortex Analyst semantic models
License: Apache-2.0
License-File: LICENSE
Keywords: snowflake,dbt,semantic-layer
Author: Matt Luizzi
Author-email: matthew.luizzi@whoop.com
Requires-Python: >=3.10,<3.12
Classifier: License :: OSI Approved :: Apache Software License
Classifier: Programming Language :: Python :: 3
Classifier: Programming Language :: Python :: 3.10
Classifier: Programming Language :: Python :: 3.11
Provides-Extra: dbt
Requires-Dist: certifi (>=2017.4.17,<2025.4.26)
Requires-Dist: click (>=8.1.7,<9.0)
Requires-Dist: numpy (>=1.24.0,<1.25.0)
Requires-Dist: packaging (>=24.2,<25.0)
Requires-Dist: python-dotenv (>=1.0.1,<1.1.0)
Requires-Dist: pyyaml (>=6.0.2,<6.1.0)
Requires-Dist: rich (>=13.9.4,<14.0)
Requires-Dist: ruamel-yaml (>=0.18.6,<0.19.0)
Requires-Dist: snowflake-connector-python[pandas,secure-local-storage] (>=3.12.3,<5.0)
Requires-Dist: tqdm (>=4.67.1,<4.68.0)
Requires-Dist: typing-extensions (>=4.12.2,<5.0)
Project-URL: Homepage, https://github.com/WhoopInc/snowflake-semantic-tools
Project-URL: Repository, https://github.com/WhoopInc/snowflake-semantic-tools
